mojang/__init__.py
mojang/_http_client.py
mojang/_types.py
mojang/_utils.py
mojang/api.py
mojang/client.py
mojang/errors.py
mojang-1.1.0.dist-info/LICENSE
mojang-1.1.0.dist-info/METADATA
mojang-1.1.0.dist-info/WHEEL
mojang-1.1.0.dist-info/top_level.txt
mojang-1.1.0.dist-info/RECORD
